Workbook

Sheet Dashboard
A1: DASHBOARD — ANÁLISIS DE CARTERA
A2: ="Tenencia total: $ "&TEXT(Resumen!B11,"#,##0")&" | TC MEP: $ "&TEXT(Resumen!C3,"#,##0.00")&" | "&TEXT(TODAY(),"dd/mm/yyyy")
A4: COMPOSICIÓN POR TIPO DE INSTRUMENTO
A5: Categoría | B5: Valor ARS | C5: % Cartera
A6: Acciones Argentina | B6: 2274835875 | C6: 0.32834979
A7: CEDEARs | B7: 419380255 | C7: 0.060533343
A8: Bonos Soberanos | B8: 1150670603 | C8: 0.16608779
A9: ONs / Corporativos | B9: 339660762 | C9: 0.049026632
A10: FCIs Pesos | B10: 1468414787 | C10: 0.21195098
A11: FCIs USD (en ARS) | B11: 8.6048169e+08 | C11: 0.12420192
A12: Letras | B12: 189416497 | C12: 0.027340376
A13: USD Líquido | B13: 116571153 | C13: 0.016825879
A14: Otros (MDP, Francés, Galicia) | B14: 105974195 | C14: 0.015296315
A17: COMPOSICIÓN POR ALyC / BROKER
A18: ALyC / Banco | B18: Valor ARS | C18: % Cartera
A19: Balanz Capital | B19: 3898578549 | C19: 0.5627208
A20: Banco Provincia | B20: 2.8069629e+09 | C20: 0.40515701
A21: MDP Bursátil | B21: 30516090 | C21: 0.0044046922
A22: Banco Francés | B22: 8592659 | C22: 0.0012402643
A23: Banco Galicia | B23: 66865446 | C23: 0.009651358
A24: USD Líquido | B24: 116571153 | C24: 0.016825879
A27: EXPOSICIÓN POR SECTOR / RIESGO
A28: Sector | B28: Valor ARS | C28: % Cartera | D28: Riesgo
A29: Energía (YPFD, PAMP, Vista, YPF ONs) | B29: 1721729829 | C29: 0.24851447 | D29: ALTO
A30: Financiero (GGAL, BMA, BBAR, SUPV, JPM) | B30: 376798490 | C30: 0.054387091 | D30: ALTO
A31: Tecnología (MSTR, NVDA, META, MELI, COIN) | B31: 245239160 | C31: 0.035397819 | D31: MUY ALTO
A32: Crypto (IBIT, ETHA) | B32: 49799300 | C32: 0.0071880306 | D32: MUY ALTO
A33: Infraestructura (TGSU2, TRAN, METR, CEPU) | B33: 201767465 | C33: 0.029123114 | D33: MEDIO
A34: Renta Fija Soberana (bonos + letras) | B34: 1340087100 | C34: 0.19342816 | D34: BAJO-MEDIO
A35: Renta Fija Corporativa (ONs) | B35: 339660762 | C35: 0.049026632 | D35: BAJO
A36: Money Market / FCIs | B36: 2.3288965e+09 | C36: 0.3361529 | D36: MUY BAJO
A37: Cash / USD Líquido | B37: 222545348 | C37: 0.032122194 | D37: MÍNIMO
A40: ANÁLISIS DE RIESGO
A41: Métrica | B41: Valor | C41: Interpretación
A42: Tenencia total ARS | B42: =Resumen!B11
A43: Tenencia total USD | B43: =Resumen!B11/Resumen!C3 | C43: ="TC MEP "&TEXT(Resumen!C3,"#,##0.00")
A45: Volatilidad anual estimada | B45: 19.0% | C45: MODERADO
A46: VaR 95% anual | B46: USD 1,525,311 | C46: 31.3% del portfolio
A47: Max Drawdown estimado | B47: 47.6% | C47: USD 2,318,102 en crisis
A49: Concentración Top 5 | B49: 34.4% | C49: ALTA
A50: Índice HHI | B50: 2031 | C50: CONCENTRADO
A52: Exposición Argentina | B52: 78.3% | C52: ALTA — riesgo país
A53: Exposición Internacional | B53: 20.2% | C53: Diversificación limitada
A55: Renta Variable | B55: 38.9% | C55: Acciones ARG + CEDEARs
A56: Renta Fija | B56: 24.2% | C56: Bonos + ONs + Letras
A57: Cash / Money Market | B57: 36.8% | C57: FCIs + USD + otros
A60: TOP 15 POSICIONES
A61: Posición | B61: Valor ARS | C61: % Cartera | D61: Broker
A62: YPFD (acciones) | B62: 1043352450 | C62: 0.15059748 | D62: Provincia + Balanz
A63: PAMP (acciones) | B63: 529557225 | C63: 0.076436286 | D63: Provincia + Balanz
A64: Raíces 24/7 | B64: 427784416 | C64: 0.061746399 | D64: Provincia
A65: BCMMA Money Market | B65: 326438863 | C65: 0.047118183 | D65: Balanz
A66: LECAPSA Lecaps FCI | B66: 318991169 | C66: 0.046043183 | D66: Balanz
A67: GGAL (acciones) | B67: 239813500 | C67: 0.034614679 | D67: Provincia + Balanz
A68: LONGPesosA | B68: 129895270 | C68: 0.018749082 | D68: Balanz
A69: Raíces Dólares Plus | B69: 1.1885428e+08 | C69: 0.017155425 | D69: Provincia
A70: YM34O (ON YPF) | B70: 117503234 | C70: 0.016960416 | D70: Balanz
A71: MSTR (CEDEAR) | B71: 105840000 | C71: 0.015276945 | D71: Balanz
A72: GD41 (bono) | B72: 99005531 | C72: 0.014290458 | D72: Balanz
A73: TTD26 (dual) | B73: 98456237 | C73: 0.014211173 | D73: Balanz
... A76: SUPV (acciones) | B76: 58753863 | C76: 0.0084805321 | D76: Balanz
A79: STRESS TEST — ESCENARIOS
A80: Escenario | B80: Impacto Estimado | C80: Pérdida USD | D80: Probabilidad
A81: Corrección leve (-10% acciones) | B81: -3.9% | C81: USD 189,368 | D81: Media
A82: Crisis moderada (2018-style) | B82: -20% | C82: USD 973,908 | D82: Baja
A83: Crisis severa (2019 PASO) | B83: -35% | C83: USD 1,704,338 | D83: Muy baja
A84: Caída crypto 50% | B84: -0.4% | C84: USD 17,501 | D84: Media
A85: Suba de tasas +5pp (bonos) | B85: -1.3% | C85: USD 64,702 | D85: Media-Baja
A86: Devaluación 30% (beneficia USD) | B86: +6.0% | C86: +USD 294,453 | D86: Baja
A89: SCORE DE RIESGO GLOBAL
A90: Score: | B90: 48 / 100 | C90: MODERADO
A91: Factores: | B91: Equity 39% | Argentina 78% | Top5 34% | Vol 19%
A94: BETA DE LA CARTERA vs MERVAL
A95: Componente | B95: Peso | C95: Beta estimada | D95: Beta ponderada
A96: Acciones ARG (Balanz) | B96: 0.072 | C96: 1.1 | D96: 0.0792
A97: Acciones ARG (Provincia) | B97: 0.245 | C97: 1.15 | D97: 0.28175
A98: CEDEARs | B98: 0.055 | C98: 0.7 | D98: 0.0385
A99: Bonos Soberanos | B99: 0.165 | C99: 0.5 | D99: 0.0825
A100: ONs / Corporativos | B100: 0.045 | C100: 0.2 | D100: 0.009
A101: FCIs Pesos | B101: 0.244 | C101: 0.05 | D101: 0.0122
A102: FCIs USD | B102: 0.105 | C102: 0.1 | D102: 0.0105
A103: Letras | B103: 0.025 | C103: 0.02 | D103: 0.0005
A104: Cash / Otros | B104: 0.044 | C104: 0 | D104: 0
A105: BETA TOTAL | D105: 0.51415
A106: Interpretación: Si el Merval cae 10%, tu cartera cae ~5.1%
A107: Beta < 1 = menos volátil que el Merval. Tu cartera tiene Beta 0.51 por el peso de FCIs y renta fija.
A110: DURATION PROMEDIO — RENTA FIJA
A111: Instrumento | B111: Valor ARS | C111: Días al Vcto | D111: Duration pond.
A112: S17A6 Lecap Abr | B112: 46591446 | C112: 9 | D112: 0.25125034
A113: TTJ26 Dual Jun | B113: 16472022 | C113: 83 | D113: 0.81918685
A114: S29Y6 Lecap May | B114: 43123993 | C114: 51 | D114: 1.3177927
A115: T30J6 Cap Jun | B115: 1366500 | C115: 83 | D115: 0.067958799
A116: TZX26 Boncer Jun | B116: 49130859 | C116: 83 | D116: 2.4433766
A117: TX26 Boncer Nov | B117: 70237475 | C117: 221 | D117: 9.3007749
A118: TTS26 Dual Sep | B118: 24612149 | C118: 160 | D118: 2.3595408
A119: S31G6 Lecap Ago | B119: 44062629 | C119: 145 | D119: 3.8282155
A120: S30O6 Lecap Oct | B120: 116406 | C120: 205 | D120: 0.014298392
A121: S30N6 Lecap Nov | B121: 44719193 | C121: 236 | D121: 6.3235933
A122: TTD26 Dual Dic | B122: 98456237 | C122: 251 | D122: 14.807267
A123: TZXD6 Boncer Dic | B123: 15768966 | C123: 251 | D123: 2.3715643
...

Sheet Historico
A1: HISTÓRICO DEL PORTFOLIO | H1: MÉTRICAS DE RENDIMIENTO
A2: Snapshots diarios — usado para calcular rendimientos histórico y diario
A4: Fecha | B4: Valor Total ($) | C4: Costo Total ($) | D4: P&L Acum ($) | E4: Var Diaria ($) | F4: Var Diaria %
A5: 46133 | B5: =0 | C5: =0 | D5: =B5-C5 | H5: Valor Actual | I5: =IFERROR(INDEX(B5:B205,MATCH(9.99E+307,B5:B205)),0)
A6: 46135 | B6: =0 | C6: =0 | D6: =IF(B6="","",B6-C6) | E6: =IF(OR(B6="",B5=""),"",B6-B5) | F6: =IF(OR(B6="",B5="",B5=0),"",(B6-B5)/B5) | H6: Costo Total | I6: =0
D7: =IF(B7="","",B7-C7) | E7: =IF(OR(B7="",B6=""),"",B7-B6) | F7: =IF(OR(B7="",B6="",B6=0),"",(B7-B6)/B6) | H7: P&L Acumulado ($) | I7: =I5-I6
D8: =IF(B8="","",B8-C8) | E8: =IF(OR(B8="",B7=""),"",B8-B7) | F8: =IF(OR(B8="",B7="",B7=0),"",(B8-B7)/B7) | H8: Rdo Total % | I8: =IF(I6>0,(I5-I6)/I6,0)
D9: =IF(B9="","",B9-C9) | E9: =IF(OR(B9="",B8=""),"",B9-B8) | F9: =IF(OR(B9="",B8="",B8=0),"",(B9-B8)/B8)
D10: =IF(B10="","",B10-C10) | E10: =IF(OR(B10="",B9=""),"",B10-B9) | F10: =IF(OR(B10="",B9="",B9=0),"",(B10-B9)/B9) | H10: Var Día ($) | I10: =IFERROR(INDEX(E5:E205,MATCH(9.99E+307,B5:B205)),0)
D11: =IF(B11="","",B11-C11) | E11: =IF(OR(B11="",B10=""),"",B11-B10) | F11: =IF(OR(B11="",B10="",B10=0),"",(B11-B10)/B10) | H11: Var Día % | I11: =IFERROR(INDEX(F5:F205,MATCH(9.99E+307,B5:B205)),0)
D12: =IF(B12="","",B12-C12) | E12: =IF(OR(B12="",B11=""),"",B12-B11) | F12: =IF(OR(B12="",B11="",B11=0),"",(B12-B11)/B11)
D13: =IF(B13="","",B13-C13) | E13: =IF(OR(B13="",B12=""),"",B13-B12) | F13: =IF(OR(B13="",B12="",B12=0),"",(B13-B12)/B12) | H13: Var Semanal % | I13: =IFERROR((I5/INDEX(B5:B205,MATCH(9.99E+307,B5:B205)-5)-1),"")
D14: =IF(B14="","",B14-C14) | E14: =IF(OR(B14="",B13=""),"",B14-B13) | F14: =IF(OR(B14="",B13="",B13=0),"",(B14-B13)/B13) | H14: Var Mensual % | I14: =IFERROR((I5/INDEX(B5:B205,MATCH(9.99E+307,B5:B205)-22)-1),"")
D15: =IF(B15="","",B15-C15) | E15: =IF(OR(B15="",B14=""),"",B15-B14) | F15: =IF(OR(B15="",B14="",B14=0),"",(B15-B14)/B14) | H15: Var YTD % | I15: =IFERROR((I5/INDEX(B5:B205,1)-1),"")
D16: =IF(B16="","",B16-C16) | E16: =IF(OR(B16="",B15=""),"",B16-B15) | F16: =IF(OR(B16="",B15="",B15=0),"",(B16-B15)/B15)
D17: =IF(B17="","",B17-C17) | E17: =IF(OR(B17="",B16=""),"",B17-B16) | F17: =IF(OR(B17="",B16="",B16=0),"",(B17-B16)/B16) | H17: Días registrados | I17: =COUNT(B5:B205)
D18: =IF(B18="","",B18-C18) | E18: =IF(OR(B18="",B17=""),"",B18-B17) | F18: =IF(OR(B18="",B17="",B17=0),"",(B18-B17)/B17) | H18: Primer registro | I18: =INDEX(A5:A205,1)
D19: =IF(B19="","",B19-C19) | E19: =IF(OR(B19="",B18=""),"",B19-B18) | F19: =IF(OR(B19="",B18="",B18=0),"",(B19-B18)/B18) | H19: Último registro | I19: =IFERROR(INDEX(A5:A205,MATCH(9.99E+307,B5:B205)),"")
D20: =IF(B20="","",B20-C20) | E20: =IF(OR(B20="",B19=""),"",B20-B19) | F20: =IF(OR(B20="",B19="",B19=0),"",(B20-B19)/B19)
D21: =IF(B21="","",B21-C21) | E21: =IF(OR(B21="",B20=""),"",B21-B20) | F21: =IF(OR(B21="",B20="",B20=0),"",(B21-B20)/B20)
D22: =IF(B22="","",B22-C22) | E22: =IF(OR(B22="",B21=""),"",B22-B21) | F22: =IF(OR(B22="",B21="",B21=0),"",(B22-B21)/B21)
D23: =IF(B23="","",B23-C23) | E23: =IF(OR(B23="",B22=""),"",B23-B22) | F23: =IF(OR(B23="",B22="",B22=0),"",(B23-B22)/B22)
D24: =IF(B24="","",B24-C24) | E24: =IF(OR(B24="",B23=""),"",B24-B23) | F24: =IF(OR(B24="",B23="",B23=0),"",(B24-B23)/B23)
D25: =IF(B25="","",B25-C25) | E25: =IF(OR(B25="",B24=""),"",B25-B24) | F25: =IF(OR(B25="",B24="",B24=0),"",(B25-B24)/B24)
D26: =IF(B26="","",B26-C26) | E26: =IF(OR(B26="",B25=""),"",B26-B25) | F26: =IF(OR(B26="",B25="",B25=0),"",(B26-B25)/B25)
D27: =IF(B27="","",B27-C27) | E27: =IF(OR(B27="",B26=""),"",B27-B26) | F27: =IF(OR(B27="",B26="",B26=0),"",(B27-B26)/B26)
D28: =IF(B28="","",B28-C28) | E28: =IF(OR(B28="",B27=""),"",B28-B27) | F28: =IF(OR(B28="",B27="",B27=0),"",(B28-B27)/B27)
D29: =IF(B29="","",B29-C29) | E29: =IF(OR(B29="",B28=""),"",B29-B28) | F29: =IF(OR(B29="",B28="",B28=0),"",(B29-B28)/B28)
D30: =IF(B30="","",B30-C30) | E30: =IF(OR(B30="",B29=""),"",B30-B29) | F30: =IF(OR(B30="",B29="",B29=0),"",(B30-B29)/B29)
D31: =IF(B31="","",B31-C31) | E31: =IF(OR(B31="",B30=""),"",B31-B30) | F31: =IF(OR(B31="",B30="",B30=0),"",(B31-B30)/B30)
... D205: =IF(B205="","",B205-C205) | E205: =IF(OR(B205="",B204=""),"",B205-B204) | F205: =IF(OR(B205="",B204="",B204=0),"",(B205-B204)/B204)

Sheet Analytics
A1: ANALYTICS DEL PORTFOLIO
A3: ASSET ALLOCATION
A4: Clase de Activo | B4: Valor ($) | C4: Peso %
A5: Acciones Argentinas | B5: =Balanz!F16+Provincia!F15 | C5: =IFERROR(B5/$B$14,0)
A6: CEDEARs | B6: =Balanz!F43+Provincia!F20 | C6: =IFERROR(B6/$B$14,0)
A7: Bonos Soberanos | B7: =Balanz!F72+Provincia!F33 | C7: =IFERROR(B7/$B$14,0)
A8: ONs / Corporativos | B8: =Balanz!F84 | C8: =IFERROR(B8/$B$14,0)
A9: FCIs Pesos | B9: =Balanz!F99+Provincia!F37 | C9: =IFERROR(B9/$B$14,0)
A10: FCIs USD (en ARS) | B10: =(Balanz!F106+Provincia!F38)*Resumen!C3 | C10: =IFERROR(B10/$B$14,0)
A11: Letras | B11: =Balanz!F118 | C11: =IFERROR(B11/$B$14,0)
A12: Otros (MDP, Galicia) | B12: =Resumen!B8+Resumen!B9 | C12: =IFERROR(B12/$B$14,0)
A13: USD Líquido | B13: =Resumen!B10 | C13: =IFERROR(B13/$B$14,0)
A14: TOTAL | B14: =SUM(B5:B13) | C14: =SUM(C5:C13)
A17: EXPOSICIÓN POR MONEDA
A18: Moneda | B18: Valor ($) | C18: Peso %
A19: ARS | B19: =Balanz!F16+Provincia!F15+Balanz!F99+Provincia!F37+Balanz!F118+SUM(Balanz!F57:F71)+Provincia!F27+Provincia!F28+Resumen!B8+Resumen!B9 | C19: =IFERROR(B19/$B$22,0)
A20: USD-Linked (BOPREAL/DL) | B20: =SUM(Balanz!F52:F56)+Provincia!F29+Provincia!F30+Provincia!F31 | C20: =IFERROR(B20/$B$22,0)
A21: USD Hard | B21: =SUM(Balanz!F47:F51)+Provincia!F24+Provincia!F25+Provincia!F26+Provincia!F32+Balanz!F84+Balanz!F43+Provincia!F20+(Balanz!F106+Provincia!F38)*Resumen!C3+Resumen!B10 | C21: =IFERROR(B21/$B$22,0)
A22: TOTAL | B22: =SUM(B19:B21) | C22: =SUM(C19:C21)
A25: DURACIÓN PORTFOLIO RENTA FIJA
A26: Bucket | B26: Valor ($) | C26: Días Promedio Vto | D26: Duración Aprox (años) | E26: Peso %
A27: Bonos Soberanos Balanz | B27: =Balanz!F72 | C27: =IFERROR(SUMPRODUCT(Balanz!F54:F71,Balanz!N54:N71)/Balanz!F72,0) | D27: =C27/365 | E27: =IFERROR(B27/SUM($B$27:$B$30),0)
A28: ONs Balanz | B28: =Balanz!F84 | C28: =IFERROR(SUMPRODUCT(Balanz!F76:F83,Balanz!N76:N83)/Balanz!F84,0) | D28: =C28/365 | E28: =IFERROR(B28/SUM($B$27:$B$30),0)
A29: Letras Balanz | B29: =Balanz!F118 | C29: =IFERROR(SUMPRODUCT(Balanz!F110:F117,Balanz!N110:N117)/Balanz!F118,0) | D29: =C29/365 | E29: =IFERROR(B29/SUM($B$27:$B$30),0)
A30: Bonos Provincia | B30: =Provincia!F33 | C30: =IFERROR(SUMPRODUCT(Provincia!F23:F32,Provincia!N23:N32)/Provincia!F33,0) | D30: =C30/365 | E30: =IFERROR(B30/SUM($B$27:$B$30),0)
A31: PROMEDIO PONDERADO | B31: =SUM(B27:B30) | C31: =IFERROR(SUMPRODUCT(B27:B30,C27:C30)/B31,0) | D31: =C31/365 | E31: =SUM(E27:E30)
A34: CALENDARIO DE VENCIMIENTOS (próximos 24 meses)
A35: Mes Vto | B35: Valor a Vencer ($) | C35: Cantidad Instrumentos | D35: Peso % RF
A36: 0-3 meses (0-90d) | B36: =SUMIFS(Balanz!F54:F71,Balanz!N54:N71,">=0",Balanz!N54:N71,"<=90")+SUMIFS(Balanz!F76:F83,Balanz!N76:N83,">=0",Balanz!N76:N83,"<=90")+SUMIFS(Balanz!F110:F117,Balanz!N110:N117,">=0",Balanz!N110:N117,"<=90")+SUMIFS(Provincia!F23:F32,Provincia!N23:N32,">=0",Provincia!N23:N32,"<=90") | C36: =COUNTIFS(Balanz!N54:N71,">=0",Balanz!N54:N71,"<=90")+COUNTIFS(Balanz!N76:N83,">=0",Balanz!N76:N83,"<=90")+COUNTIFS(Balanz!N110:N117,">=0",Balanz!N110:N117,"<=90")+COUNTIFS(Provincia!N23:N32,">=0",Provincia!N23:N32,"<=90") | D36: =IFERROR(B36/$B$43,0)
A37: 3-6 meses (91-180d) | B37: =SUMIFS(Balanz!F54:F71,Balanz!N54:N71,">=91",Balanz!N54:N71,"<=180")+SUMIFS(Balanz!F76:F83,Balanz!N76:N83,">=91",Balanz!N76:N83,"<=180")+SUMIFS(Balanz!F110:F117,Balanz!N110:N117,">=91",Balanz!N110:N117,"<=180")+SUMIFS(Provincia!F23:F32,Provincia!N23:N32,">=91",Provincia!N23:N32,"<=180") | C37: =COUNTIFS(Balanz!N54:N71,">=91",Balanz!N54:N71,"<=180")+COUNTIFS(Balanz!N76:N83,">=91",Balanz!N76:N83,"<=180")+COUNTIFS(Balanz!N110:N117,">=91",Balanz!N110:N117,"<=180")+COUNTIFS(Provincia!N23:N32,">=91",Provincia!N23:N32,"<=180") | D37: =IFERROR(B37/$B$43,0)
A38: 6-12 meses (181-365d) | B38: =SUMIFS(Balanz!F54:F71,Balanz!N54:N71,">=181",Balanz!N54:N71,"<=365")+SUMIFS(Balanz!F76:F83,Balanz!N76:N83,">=181",Balanz!N76:N83,"<=365")+SUMIFS(Balanz!F110:F117,Balanz!N110:N117,">=181",Balanz!N110:N117,"<=365")+SUMIFS(Provincia!F23:F32,Provincia!N23:N32,">=181",Provincia!N23:N32,"<=365") | C38: =COUNTIFS(Balanz!N54:N71,">=181",Balanz!N54:N71,"<=365")+COUNTIFS(Balanz!N76:N83,">=181",Balanz!N76:N83,"<=365")+COUNTIFS(Balanz!N110:N117,">=181",Balanz!N110:N117,"<=365")+COUNTIFS(Provincia!N23:N32,">=181",Provincia!N23:N32,"<=365") | D38: =IFERROR(B38/$B$43,0)
A39: 12-18 meses (366-545d) | B39: =SUMIFS(Balanz!F54:F71,Balanz!N54:N71,">=366",Balanz!N54:N71,"<=545")+SUMIFS(Balanz!F76:F83,Balanz!N76:N83,">=366",Balanz!N76:N83,"<=545")+SUMIFS(Balanz!F110:F117,Balanz!N110:N117,">=366",Balanz!N110:N117,"<=545")+SUMIFS(Provincia!F23:F32,Provincia!N23:N32,">=366",Provincia!N23:N32,"<=545") | C39: =COUNTIFS(Balanz!N54:N71,">=366",Balanz!N54:N71,"<=545")+COUNTIFS(Balanz!N76:N83,">=366",Balanz!N76:N83,"<=545")+COUNTIFS(Balanz!N110:N117,">=366",Balanz!N110:N117,"<=545")+COUNTIFS(Provincia!N23:N32,">=366",Provincia!N23:N32,"<=545") | D39: =IFERROR(B39/$B$43,0)
A40: 18-24 meses (546-730d) | B40: =SUMIFS(Balanz!F54:F71,Balanz!N54:N71,">=546",Balanz!N54:N71,"<=730")+SUMIFS(Balanz!F76:F83,Balanz!N76:N83,">=546",Balanz!N76:N83,"<=730")+SUMIFS(Balanz!F110:F117,Balanz!N110:N117,">=546",Balanz!N110:N117,"<=730")+SUMIFS(Provincia!F23:F32,Provincia!N23:N32,">=546",Provincia!N23:N32,"<=730") | C40: =COUNTIFS(Balanz!N54:N71,">=546",Balanz!N54:N71,"<=730")+COUNTIFS(Balanz!N76:N83,">=546",Balanz!N76:N83,"<=730")+COUNTIFS(Balanz!N110:N117,">=546",Balanz!N110:N117,"<=730")+COUNTIFS(Provincia!N23:N32,">=546",Provincia!N23:N32,"<=730") | D40: =IFERROR(B40/$B$43,0)
A41: 24-36 meses (731-1095d) | B41: =SUMIFS(Balanz!F54:F71,Balanz!N54:N71,">=731",Balanz!N54:N71,"<=1095")+SUMIFS(Balanz!F76:F83,Balanz!N76:N83,">=731",Balanz!N76:N83,"<=1095")+SUMIFS(Balanz!F110:F117,Balanz!N110:N117,">=731",Balanz!N110:N117,"<=1095")+SUMIFS(Provincia!F23:F32,Provincia!N23:N32,">=731",Provincia!N23:N32,"<=1095") | C41: =COUNTIFS(Balanz!N54:N71,">=731",Balanz!N54:N71,"<=1095")+COUNTIFS(Balanz!N76:N83,">=731",Balanz!N76:N83,"<=1095")+COUNTIFS(Balanz!N110:N117,">=731",Balanz!N110:N117,"<=1095")+COUNTIFS(Provincia!N23:N32,">=731",Provincia!N23:N32,"<=1095") | D41: =IFERROR(B41/$B$43,0)
A42: Más de 36 meses (>1095d) | B42: =SUMIFS(Balanz!F54:F71,Balanz!N54:N71,">=1096",Balanz!N54:N71,"<=99999")+SUMIFS(Balanz!F76:F83,Balanz!N76:N83,">=1096",Balanz!N76:N83,"<=99999")+SUMIFS(Balanz!F110:F117,Balanz!N110:N117,">=1096",Balanz!N110:N117,"<=99999")+SUMIFS(Provincia!F23:F32,Provincia!N23:N32,">=1096",Provincia!N23:N32,"<=99999") | C42: =COUNTIFS(Balanz!N54:N71,">=1096",Balanz!N54:N71,"<=99999")+COUNTIFS(Balanz!N76:N83,">=1096",Balanz!N76:N83,"<=99999")+COUNTIFS(Balanz!N110:N117,">=1096",Balanz!N110:N117,"<=99999")+COUNTIFS(Provincia!N23:N32,">=1096",Provincia!N23:N32,"<=99999") | D42: =IFERROR(B42/$B$43,0)
A43: TOTAL RF | B43: =SUM(B36:B42) | C43: =SUM(C36:C42) | D43: =SUM(D36:D42)

Sheet Resumen
A1: MONITOR DE INVERSIONES
A2: Casimiro Félix Toyos e Hijos S.A.
A3: TC MEP: $ 1,419.25 | Cable: $ 1.471,87 | B3: TC MEP → | C3: 1419.25 | G3: RENDIMIENTO PORTFOLIO
A5: ALyC / Banco | B5: Valor Actual | C5: Costo | D5: Rendimiento $ | E5: Rdo % | G5: Rdo Total Histórico % | H5: =IF(C11>0,(B11-C11)/C11,0)
A6: Balanz Capital | B6: =Balanz!F16+Balanz!F43+Balanz!F72+Balanz!F84+Balanz!F99+(Balanz!F106*C3)+Balanz!F118 | C6: =Balanz!G16+Balanz!G43+Balanz!G72+Balanz!G84+Balanz!G99+(Balanz!G106*C3)+Balanz!G118 | D6: =B6-C6 | E6: =IF(C6>0,(B6-C6)/C6,0) | G6: Rdo Total Histórico $ | H6: =B11-C11
A7: Banco Provincia | B7: =Provincia!F15+Provincia!F20+Provincia!F33+Provincia!F37+(Provincia!F38*C3) | C7: =Provincia!G15+Provincia!G20+Provincia!G33+Provincia!G37+(Provincia!G38*C3) | D7: =B7-C7 | E7: =IF(C7>0,(B7-C7)/C7,0) | G7: Var Día % | H7: =IFERROR(Historico!I11,0)
A8: MDP Bursátil | B8: 30516090 | C8: 22377937 | D8: =B8-C8 | E8: =IF(C8>0,(B8-C8)/C8,0) | G8: Var Día $ | H8: =IFERROR(Historico!I10,0)
A9: Banco Galicia | B9: 66865446 | C9: 66865446 | D9: =B9-C9 | E9: =IF(C9>0,(B9-C9)/C9,0) | G9: Var Mensual % | H9: =IFERROR(Historico!I14,0)
A10: USD — Dólares, M/E y CV | B10: 116571153 | C10: 116571153 | D10: =B10-C10 | E10: =IF(C10>0,(B10-C10)/C10,0) | G10: Var YTD % | H10: =IFERROR(Historico!I15,0)
A11: TENENCIA TOTAL | B11: =SUM(B6:B10) | C11: =SUM(C6:C10) | D11: =SUM(D6:D10) | E11: =IF(C11>0,(B11-C11)/C11,0)

Sheet Balanz
A1: BALANZ CAPITAL
A2: TC MEP: $ 1,419.25
A4: ACCIONES
A5: Ticker | B5: Descripción | C5: Cantidad | D5: PPC Compra | E5: Precio Vivo | F5: Valor Actual | G5: Costo Total | H5: P&L $ | I5: P&L % | J5: Var Día % | K5: P&L USD | L5: Peso % | M5: Vencimiento | N5: Días
A6: AUSO | B6: Autopista del Sol | C6: 2773 | D6: 2920 | E6: =googlefinance("BCBA:AUSO","price") | F6: =C6*E6 | G6: =C6*D6 | H6: =F6-G6 | I6: =IF(G6>0,(F6-G6)/G6,0) | K6: =IF(H6<>0,H6/Resumen!$C$3,0) | L6: =IF(F6<>0,F6/Resumen!$B$11,0)
A7: BPAT | B7: Banco Patagonia | C7: 5926 | D7: 2354.41 | E7: =googlefinance("BCBA:BPAT","price") | F7: =C7*E7 | G7: =C7*D7 | H7: =F7-G7 | I7: =IF(G7>0,(F7-G7)/G7,0) | K7: =IF(H7<>0,H7/Resumen!$C$3,0) | L7: =IF(F7<>0,F7/Resumen!$B$11,0)
A8: CEPU | B8: Central Puerto | C8: 5905 | D8: 2540 | E8: =googlefinance("BCBA:CEPU","price") | F8: =C8*E8 | G8: =C8*D8 | H8: =F8-G8 | I8: =IF(G8>0,(F8-G8)/G8,0) | K8: =IF(H8<>0,H8/Resumen!$C$3,0) | L8: =IF(F8<>0,F8/Resumen!$B$11,0)
A9: METR | B9: Metrogas | C9: 14877 | D9: 1765.57 | E9: =googlefinance("BCBA:METR","price") | F9: =C9*E9 | G9: =C9*D9 | H9: =F9-G9 | I9: =IF(G9>0,(F9-G9)/G9,0) | K9: =IF(H9<>0,H9/Resumen!$C$3,0) | L9: =IF(F9<>0,F9/Resumen!$B$11,0)
A10: MIRG | B10: Mirgor | C10: 856.3 | D10: 24624.51 | E10: =googlefinance("BCBA:MIRG","price") | F10: =C10*E10 | G10: =C10*D10 | H10: =F10-G10 | I10: =IF(G10>0,(F10-G10)/G10,0) | K10: =IF(H10<>0,H10/Resumen!$C$3,0) | L10: =IF(F10<>0,F10/Resumen!$B$11,0)
A11: PAMP | B11: Pampa Energía | C11: 16651 | D11: 3153.43 | E11: =googlefinance("BCBA:PAMP","price") | F11: =C11*E11 | G11: =C11*D11 | H11: =F11-G11 | I11: =IF(G11>0,(F11-G11)/G11,0) | K11: =IF(H11<>0,H11/Resumen!$C$3,0) | L11: =IF(F11<>0,F11/Resumen!$B$11,0)
A12: SUPV | B12: Grupo Supervielle | C12: 20173 | D12: 3006.98 | E12: =googlefinance("BCBA:SUPV","price") | F12: =C12*E12 | G12: =C12*D12 | H12: =F12-G12 | I12: =IF(G12>0,(F12-G12)/G12,0) | K12: =IF(H12<>0,H12/Resumen!$C$3,0) | L12: =IF(F12<>0,F12/Resumen!$B$11,0)
A13: TGSU2 | B13: TGS | C13: 5292 | D13: 7893.28 | E13: =googlefinance("BCBA:TGSU2","price") | F13: =C13*E13 | G13: =C13*D13 | H13: =F13-G13 | I13: =IF(G13>0,(F13-G13)/G13,0) | K13: =IF(H13<>0,H13/Resumen!$C$3,0) | L13: =IF(F13<>0,F13/Resumen!$B$11,0)
A14: TXAR | B14: Ternium Argentina | C14: 20545 | D14: 843.94 | E14: =googlefinance("BCBA:TXAR","price") | F14: =C14*E14 | G14: =C14*D14 | H14: =F14-G14 | I14: =IF(G14>0,(F14-G14)/G14,0) | K14: =IF(H14<>0,H14/Resumen!$C$3,0) | L14: =IF(F14<>0,F14/Resumen!$B$11,0)
A15: YPFD | B15: YPF S.A. | C15: 2682 | D15: 34532.44 | E15: =googlefinance("BCBA:YPFD","price") | F15: =C15*E15 | G15: =C15*D15 | H15: =F15-G15 | I15: =IF(G15>0,(F15-G15)/G15,0) | K15: =IF(H15<>0,H15/Resumen!$C$3,0) | L15: =IF(F15<>0,F15/Resumen!$B$11,0)
A16: SUBTOTAL | F16: =SUM(F6:F15) | G16: =SUM(G6:G15) | H16: =F16-G16 | I16: =IF(G16>0,(F16-G16)/G16,0) | K16: =SUM(K6:K15) | L16: =SUM(L6:L15)
A18: CEDEARs
A19: Ticker | B19: Descripción | C19: Cantidad | D19: PPC Compra | E19: Precio Vivo | F19: Valor Actual | G19: Costo Total | H19: P&L $ | I19: P&L % | J19: Var Día % | K19: P&L USD | L19: Peso % | M19: Vencimiento | N19: Días
A20: BRKB | B20: Berkshire Hathaway | C20: 865 | D20: 34680 | E20: =googlefinance("BCBA:BRKB","price") | F20: =C20*E20 | G20: =C20*D20 | H20: =F20-G20 | I20: =IF(G20>0,(F20-G20)/G20,0) | K20: =IF(H20<>0,H20/Resumen!$C$3,0) | L20: =IF(F20<>0,F20/Resumen!$B$11,0)
A21: COIN | B21: Coinbase | C21: 2880 | D21: 13735.57 | E21: =googlefinance("BCBA:COIN","price") | F21: =C21*E21 | G21: =C21*D21 | H21: =F21-G21 | I21: =IF(G21>0,(F21-G21)/G21,0) | K21: =IF(H21<>0,H21/Resumen!$C$3,0) | L21: =IF(F21<>0,F21/Resumen!$B$11,0)
A22: CVX | B22: Chevron | C22: 10 | D22: 18110 | E22: =googlefinance("BCBA:CVX","price") | F22: =C22*E22 | G22: =C22*D22 | H22: =F22-G22 | I22: =IF(G22>0,(F22-G22)/G22,0) | K22: =IF(H22<>0,H22/Resumen!$C$3,0) | L22: =IF(F22<>0,F22/Resumen!$B$11,0)
A23: ETHA | B23: iShares Ethereum | C23: 1350 | D23: 7250 | E23: =googlefinance("BCBA:ETHA","price") | F23: =C23*E23 | G23: =C23*D23 | H23: =F23-G23 | I23: =IF(G23>0,(F23-G23)/G23,0) | K23: =IF(H23<>0,H23/Resumen!$C$3,0) | L23: =IF(F23<>0,F23/Resumen!$B$11,0)
A24: GLOB | B24: Globant | C24: 100 | D24: 4032.5 | E24: =googlefinance("BCBA:GLOB","price") | F24: =C24*E24 | G24: =C24*D24 | H24: =F24-G24 | I24: =IF(G24>0,(F24-G24)/G24,0) | K24: =IF(H24<>0,H24/Resumen!$C$3,0) | L24: =IF(F24<>0,F24/Resumen!$B$11,0)
A25: IBIT | B25: iShares Bitcoin | C25: 7420 | D25: 8656.7 | E25: =googlefinance("BCBA:IBIT","price") | F25: =C25*E25 | G25: =C25*D25 | H25: =F25-G25 | I25: =IF(G25>0,(F25-G25)/G25,0) | K25: =IF(H25<>0,H25/Resumen!$C$3,0) | L25: =IF(F25<>0,F25/Resumen!$B$11,0)
A26: JPM | B26: JP Morgan | C26: 600 | D26: 33283.8 | E26: =googlefinance("BCBA:JPM","price") | F26: =C26*E26 | G26: =C26*D26 | H26: =F26-G26 | I26: =IF(G26>0,(F26-G26)/G26,0) | K26: =IF(H26<>0,H26/Resumen!$C$3,0) | L26: =IF(F26<>0,F26/Resumen!$B$11,0)
A27: KO | B27: Coca-Cola | C27: 10 | D27: 22950 | E27: =googlefinance("BCBA:KO","price") | F27: =C27*E27 | G27: =C27*D27 | H27: =F27-G27 | I27: =IF(G27>0,(F27-G27)/G27,0) | K27: =IF(H27<>0,H27/Resumen!$C$3,0) | L27: =IF(F27<>0,F27/Resumen!$B$11,0)
A28: LLY | B28: Eli Lilly | C28: 1175 | D28: 29732.44 | E28: =googlefinance("BCBA:LLY","price") | F28: =C28*E28 | G28: =C28*D28 | H28: =F28-G28 | I28: =IF(G28>0,(F28-G28)/G28,0) | K28: =IF(H28<>0,H28/Resumen!$C$3,0) | L28: =IF(F28<>0,F28/Resumen!$B$11,0)
A29: LMT | B29: Lockheed Martin | C29: 5 | D29: 47400 | E29: =googlefinance("BCBA:LMT","price") | F29: =C29*E29 | G29: =C29*D29 | H29: =F29-G29 | I29: =IF(G29>0,(F29-G29)/G29,0) | K29: =IF(H29<>0,H29/Resumen!$C$3,0) | L29: =IF(F29<>0,F29/Resumen!$B$11,0)
A30: MELI | B30: MercadoLibre | C30: 1862 | D30: 26824.79 | E30: =googlefinance("BCBA:MELI","price") | F30: =C30*E30 | G30: =C30*D30 | H30: =F30-G30 | I30: =IF(G30>0,(F30-G30)/G30,0) | K30: =IF(H30<>0,H30/Resumen!$C$3,0) | L30: =IF(F30<>0,F30/Resumen!$B$11,0)
A31: META | B31: Meta Platforms | C31: 720 | D31: 41599.72 | E31: =googlefinance("BCBA:META","price") | F31: =C31*E31 | G31: =C31*D31 | H31: =F31-G31 | I31: =IF(G31>0,(F31-G31)/G31,0) | K31: =IF(H31<>0,H31/Resumen!$C$3,0) | L31: =IF(F31<>0,F31/Resumen!$B$11,0)
A32: MSFT | B32: Microsoft | C32: 10 | D32: 19610 | E32: =googlefinance("BCBA:MSFT","price") | F32: =C32*E32 | G32: =C32*D32 | H32: =F32-G32 | I32: =IF(G32>0,(F32-G32)/G32,0) | K32: =IF(H32<>0,H32/Resumen!$C$3,0) | L32: =IF(F32<>0,F32/Resumen!$B$11,0)
A33: MSTR | B33: MicroStrategy | C33: 11200 | D33: 16417.39 | E33: =googlefinance("BCBA:MSTR","price") | F33: =C33*E33 | G33: =C33*D33 | H33: =F33-G33 | I33: =IF(G33>0,(F33-G33)/G33,0) | K33: =IF(H33<>0,H33/Resumen!$C$3,0) | L33: =IF(F33<>0,F33/Resumen!$B$11,0)
A34: NFLX | B34: Netflix | C34: 200 | D34: 2900 | E34: =googlefinance("BCBA:NFLX","price") | F34: =C34*E34 | G34: =C34*D34 | H34: =F34-G34 | I34: =IF(G34>0,(F34-G34)/G34,0) | K34: =IF(H34<>0,H34/Resumen!$C$3,0) | L34: =IF(F34<>0,F34/Resumen!$B$11,0)
A35: NVDA | B35: Nvidia | C35: 4389 | D35: 11389.24 | E35: =googlefinance("BCBA:NVDA","price") | F35: =C35*E35 | G35: =C35*D35 | H35: =F35-G35 | I35: =IF(G35>0,(F35-G35)/G35,0) | K35: =IF(H35<>0,H35/Resumen!$C$3,0) | L35: =IF(F35<>0,F35/Resumen!$B$11,0)
A36: PBR | B36: Petrobras | C36: 10 | D36: 28260 | E36: =googlefinance("BCBA:PBR","price") | F36: =C36*E36 | G36: =C36*D36 | H36: =F36-G36 | I36: =IF(G36>0,(F36-G36)/G36,0) | K36: =IF(H36<>0,H36/Resumen!$C$3,0) | L36: =IF(F36<>0,F36/Resumen!$B$11,0)
A37: RTX | B37: Raytheon | C37: 5 | D37: 60575 | E37: =googlefinance("BCBA:RTX","price") | F37: =C37*E37 | G37: =C37*D37 | H37: =F37-G37 | I37: =IF(G37>0,(F37-G37)/G37,0) | K37: =IF(H37<>0,H37/Resumen!$C$3,0) | L37: =IF(F37<>0,F37/Resumen!$B$11,0)
A38: SLV | B38: iShares Silver | C38: 50 | D38: 20640 | E38: =googlefinance("BCBA:SLV","price") | F38: =C38*E38 | G38: =C38*D38 | H38: =F38-G38 | I38: =IF(G38>0,(F38-G38)/G38,0) | K38: =IF(H38<>0,H38/Resumen!$C$3,0) | L38: =IF(F38<>0,F38/Resumen!$B$11,0)
A39: V | B39: Visa | C39: 1005 | D39: 28789.62 | E39: =googlefinance("BCBA:V","price") | F39: =C39*E39 | G39: =C39*D39 | H39: =F39-G39 | I39: =IF(G39>0,(F39-G39)/G39,0) | K39: =IF(H39<>0,H39/Resumen!$C$3,0) | L39: =IF(F39<>0,F39/Resumen!$B$11,0)
A40: VIST | B40: Vista Energy | C40: 38 | D40: 27760 | E40: =googlefinance("BCBA:VIST","price") | F40: =C40*E40 | G40: =C40*D40 | H40: =F40-G40 | I40: =IF(G40>0,(F40-G40)/G40,0) | K40: =IF(H40<>0,H40/Resumen!$C$3,0) | L40: =IF(F40<>0,F40/Resumen!$B$11,0)
A41: WMT | B41: Walmart | C41: 100 | D41: 10397.39 | E41: =googlefinance("BCBA:WMT","price") | F41: =C41*E41 | G41: =C41*D41 | H41: =F41-G41 | I41: =IF(G41>0,(F41-G41)/G41,0) | K41: =IF(H41<>0,H41/Resumen!$C$3,0) | L41: =IF(F41<>0,F41/Resumen!$B$11,0)
A42: XOM | B42: Exxon Mobil | C42: 50 | D42: 22270 | E42: =googlefinance("BCBA:XOM","price") | F42: =C42*E42 | G42: =C42*D42 | H42: =F42-G42 | I42: =IF(G42>0,(F42-G42)/G42,0) | K42: =IF(H42<>0,H42/Resumen!$C$3,0) | L42: =IF(F42<>0,F42/Resumen!$B$11,0)
A43: SUBTOTAL | F43: =SUM(F20:F42) | G43: =SUM(G20:G42) | H43: =F43-G43 | I43: =IF(G43>0,(F43-G43)/G43,0) | K43: =SUM(K20:K42) | L43: =SUM(L20:L42)
A45: BONOS SOBERANOS
A46: Ticker | B46: Descripción | C46: Cantidad | D46: PPC Compra | E46: Precio Vivo | F46: Valor Actual | G46: Costo Total | H46: P&L $ | I46: P&L % | J46: Var Día % | K46: P&L USD | L46: Peso % | M46: Vencimiento | N46: Días
A47: AE38 | B47: Bono Arg USD 2038 | C47: 21194 | D47: 1001.2 | E47: 1142.8 | F47: =C47*E47 | G47: =C47*D47 | H47: =F47-G47 | I47: =IF(G47>0,(F47-G47)/G47,0) | K47: =IF(H47<>0,H47/Resumen!$C$3,0) | L47: =IF(F47<>0,F47/Resumen!$B$11,0) | M47: 2038-01-09 | N47: 4294
A48: AL30 | B48: Bono Arg USD 2030 | C48: 40000 | D48: 388.43 | E48: 906 | F48: =C48*E48 | G48: =C48*D48 | H48: =F48-G48 | I48: =IF(G48>0,(F48-G48)/G48,0) | K48: =IF(H48<>0,H48/Resumen!$C$3,0) | L48: =IF(F48<>0,F48/Resumen!$B$11,0) | M48: 2030-07-09 | N48: 1553
A49: GD35 | B49: Global USD 2035 | C49: 32881 | D49: 568.4 | E49: 1134.2 | F49: =C49*E49 | G49: =C49*D49 | H49: =F49-G49 | I49: =IF(G49>0,(F49-G49)/G49,0) | K49: =IF(H49<>0,H49/Resumen!$C$3,0) | L49: =IF(F49<>0,F49/Resumen!$B$11,0) | M49: 2035-07-09 | N49: 3379
A50: GD38 | B50: Global USD 2038 | C50: 1674 | D50: 708.04 | E50: 1182.3 | F50: =C50*E50 | G50: =C50*D50 | H50: =F50-G50 | I50: =IF(G50>0,(F50-G50)/G50,0) | K50: =IF(H50<>0,H50/Resumen!$C$3,0) | L50: =IF(F50<>0,F50/Resumen!$B$11,0) | M50: 2038-01-09 | N50: 4294
A51: GD41 | B51: Global USD 2041 | C51: 95852 | D51: 871.37 | E51: 1050 | F51: =C51*E51 | G51: =C51*D51 | H51: =F51-G51 | I51: =IF(G51>0,(F51-G51)/G51,0) | K51: =IF(H51<>0,H51/Resumen!$C$3,0) | L51: =IF(F51<>0,F51/Resumen!$B$11,0) | M51: 2041-07-09 | N51: 5571
A52: BPOA7 | B52: Bopreal 1A 2027 | C52: 35817 | D52: 1477.7 | E52: 1476.9 | F52: =C52*E52 | G52: =C52*D52 | H52: =F52-G52 | I52: =IF(G52>0,(F52-G52)/G52,0) | K52: =IF(H52<>0,H52/Resumen!$C$3,0) | L52: =IF(F52<>0,F52/Resumen!$B$11,0) | M52: 2027-10-31 | N52: 571
A53: BPOB7 | B53: Bopreal 1B 2027 | C53: 10607 | D53: 1415.58 | E53: 1473 | F53: =C53*E53 | G53: =C53*D53 | H53: =F53-G53 | I53: =IF(G53>0,(F53-G53)/G53,0) | K53: =IF(H53<>0,H53/Resumen!$C$3,0) | L53: =IF(F53<>0,F53/Resumen!$B$11,0) | M53: 2027-10-31 | N53: 571
A54: BPOC7 | B54: Bopreal 1C 2027 | C54: 15294 | D54: 1387.77 | E54: 1470 | F54: =C54*E54 | G54: =C54*D54 | H54: =F54-G54 | I54: =IF(G54>0,(F54-G54)/G54,0) | K54: =IF(H54<>0,H54/Resumen!$C$3,0) | L54: =IF(F54<>0,F54/Resumen!$B$11,0) | M54: 2027-10-31 | N54: 571
A55: BPOD7 | B55: Bopreal 1D 2027 | C55: 26310 | D55: 1400.92 | E55: 1473.8 | F55: =C55*E55 | G55: =C55*D55 | H55: =F55-G55 | I55: =IF(G55>0,(F55-G55)/G55,0) | K55: =IF(H55<>0,H55/Resumen!$C$3,0) | L55: =IF(F55<>0,F55/Resumen!$B$11,0) | M55: 2027-10-31 | N55: 571
A56: BPY26 | B56: Bopreal S3 2026 | C56: 19800 | D56: 503 | E56: 521.4 | F56: =C56*E56 | G56: =C56*D56 | H56: =F56-G56 | I56: =IF(G56>0,(F56-G56)/G56,0) | K56: =IF(H56<>0,H56/Resumen!$C$3,0) | L56: =IF(F56<>0,F56/Resumen!$B$11,0) | M56: 2026-05-31 | N56: 53
A57: TTD26 | B57: Dual Dic 2026 | C57: 64646249 | D57: 1.04 | E57: 1.54 | F57: =C57*E57 | G57: =C57*D57 | H57: =F57-G57 | I57: =IF(G57>0,(F57-G57)/G57,0) | K57: =IF(H57<>0,H57/Resumen!$C$3,0) | L57: =IF(F57<>0,F57/Resumen!$B$11,0) | M57: 2026-12-15 | N57: 251
A58: TTJ26 | B58: Dual Jun 2026 | C58: 10703068 | D58: 1.17 | E58: 1.56 | F58: =C58*E58 | G58: =C58*D58 | H58: =F58-G58 | I58: =IF(G58>0,(F58-G58)/G58,0) | K58: =IF(H58<>0,H58/Resumen!$C$3,0) | L58: =IF(F58<>0,F58/Resumen!$B$11,0) | M58: 2026-06-30 | N58: 83
... A71: TO26 | B71: Bono ARS Oct 2026 | C71: 22526934 | D71: 0.94 | E71: 0.96 | F71: =C71*E71 | G71: =C71*D71 | H71: =F71-G71 | I71: =IF(G71>0,(F71-G71)/G71,0) | K71: =IF(H71<>0,H71/Resumen!$C$3,0) | L71: =IF(F71<>0,F71/Resumen!$B$11,0) | M71: 2026-10-17 | N71: 192
A72: SUBTOTAL | F72: =SUM(F47:F71) | G72: =SUM(G47:G71) | H72: =F72-G72 | I72: =IF(G72>0,(F72-G72)/G72,0) | K72: =SUM(K47:K71) | L72: =SUM(L47:L71)
A74: ONs / CORPORATIVOS
A75: Ticker | B75: Descripción | C75: Cantidad | D75: PPC Compra | E75: Precio Vivo | F75: Valor Actual | G75: Costo Total | H75: P&L $ | I75: P&L % | J75: Var Día % | K75: P&L USD | L75: Peso % | M75: Vencimiento | N75: Días
A76: IRCFO | B76: IRSA 8.75% 2028 | C76: 23042 | D76: 831.93 | E76: 1007.2 | F76: =C76*E76 | G76: =C76*D76 | H76: =F76-G76 | I76: =IF(G76>0,(F76-G76)/G76,0) | K76: =IF(H76<>0,H76/Resumen!$C$3,0) | L76: =IF(F76<>0,F76/Resumen!$B$11,0) | M76: 2028-06-22 | N76: 806
A77: IRCPO | B77: IRSA Inv 8% 2035 | C77: 42841 | D77: 1413.09 | E77: 1557.4 | F77: =C77*E77 | G77: =C77*D77 | H77: =F77-G77 | I77: =IF(G77>0,(F77-G77)/G77,0) | K77: =IF(H77<>0,H77/Resumen!$C$3,0) | L77: =IF(F77<>0,F77/Resumen!$B$11,0) | M77: 2035-03-31 | N77: 3279
A78: PLC4O | B78: Pluspetrol 8.5% 2032 | C78: 12000 | D78: 1498.85 | E78: 1592 | F78: =C78*E78 | G78: =C78*D78 | H78: =F78-G78 | I78: =IF(G78>0,(F78-G78)/G78,0) | K78: =IF(H78<>0,H78/Resumen!$C$3,0) | L78: =IF(F78<>0,F78/Resumen!$B$11,0) | M78: 2032-05-29 | N78: 2243
A79: TLCPO | B79: Telecom 9.25% 2033 | C79: 35602 | D79: 1617.94 | E79: 1630.3 | F79: =C79*E79 | G79: =C79*D79 | H79: =F79-G79 | I79: =IF(G79>0,(F79-G79)/G79,0) | K79: =IF(H79<>0,H79/Resumen!$C$3,0) | L79: =IF(F79<>0,F79/Resumen!$B$11,0) | M79: 2033-05-28 | N79: 2607
A80: VSCVO | B80: Vista 8.5% 2033 | C80: 9000 | D80: 1537.87 | E80: 1616.1 | F80: =C80*E80 | G80: =C80*D80 | H80: =F80-G80 | I80: =IF(G80>0,(F80-G80)/G80,0) | K80: =IF(H80<>0,H80/Resumen!$C$3,0) | L80: =IF(F80<>0,F80/Resumen!$B$11,0) | M80: 2033-06-10 | N80: 2620
A81: YFCJO | B81: YPF Energía 7.875% 2032 | C81: 10000 | D81: 1416.51 | E81: 1518 | F81: =C81*E81 | G81: =C81*D81 | H81: =F81-G81 | I81: =IF(G81>0,(F81-G81)/G81,0) | K81: =IF(H81<>0,H81/Resumen!$C$3,0) | L81: =IF(F81<>0,F81/Resumen!$B$11,0) | M81: 2032-10-16 | N81: 2383
A82: YM34O | B82: YPF 8.25% 2034 | C82: 75833 | D82: 1467.63 | E82: 1579.8 | F82: =C82*E82 | G82: =C82*D82 | H82: =F82-G82 | I82: =IF(G82>0,(F82-G82)/G82,0) | K82: =IF(H82<>0,H82/Resumen!$C$3,0) | L82: =IF(F82<>0,F82/Resumen!$B$11,0) | M82: 2034-01-17 | N82: 2841
A83: YMCIO | B83: YPF 2.5% 2029 | C83: 17899 | D83: 1118.28 | E83: 1565.5 | F83: =C83*E83 | G83: =C83*D83 | H83: =F83-G83 | I83: =IF(G83>0,(F83-G83)/G83,0) | K83: =IF(H83<>0,H83/Resumen!$C$3,0) | L83: =IF(F83<>0,F83/Resumen!$B$11,0) | M83: 2029-06-30 | N83: 1179
A84: SUBTOTAL | F84: =SUM(F76:F83) | G84: =SUM(G76:G83) | H84: =F84-G84 | I84: =IF(G84>0,(F84-G84)/G84,0) | K84: =SUM(K76:K83) | L84: =SUM(L76:L83)
A86: FCIs PESOS
A87: Ticker | B87: Descripción | C87: Cantidad | D87: PPC Compra | E87: Precio Vivo | F87: Valor Actual | G87: Costo Total | H87: P&L $ | I87: P&L % | J87: Var Día % | K87: P&L USD | L87: Peso % | M87: Vencimiento | N87: Días
A88: BCAHA | B88: Ahorro CP | C88: 356022.16 | D88: 223.3 | E88: 227.48 | F88: =C88*E88 | G88: =C88*D88 | H88: =F88-G88 | I88: =IF(G88>0,(F88-G88)/G88,0) | K88: =IF(H88<>0,H88/Resumen!$C$3,0) | L88: =IF(F88<>0,F88/Resumen!$B$11,0)
A89: BCAPYB | B89: Capital Pymes | C89: 557800.86 | D89: 59.12 | E89: 68.97 | F89: =C89*E89 | G89: =C89*D89 | H89: =F89-G89 | I89: =IF(G89>0,(F89-G89)/G89,0) | K89: =IF(H89<>0,H89/Resumen!$C$3,0) | L89: =IF(F89<>0,F89/Resumen!$B$11,0)
A90: BCMMA | B90: Money Market | C90: 36262009 | D90: 11.11 | E90: 11.66 | F90: =C90*E90 | G90: =C90*D90 | H90: =F90-G90 | I90: =IF(G90>0,(F90-G90)/G90,0) | K90: =IF(H90<>0,H90/Resumen!$C$3,0) | L90: =IF(F90<>0,F90/Resumen!$B$11,0)
A91: BCRFA | B91: Dólar Linked | C91: 217256.11 | D91: 222.64 | E91: 219.69 | F91: =C91*E91 | G91: =C91*D91 | H91: =F91-G91 | I91: =IF(G91>0,(F91-G91)/G91,0) | K91: =IF(H91<>0,H91/Resumen!$C$3,0) | L91: =IF(F91<>0,F91/Resumen!$B$11,0)
A92: INSTITUA | B92: Inflation Linked | C92: 695624.18 | D92: 109.47 | E92: 112.69 | F92: =C92*E92 | G92: =C92*D92 | H92: =F92-G92 | I92: =IF(G92>0,(F92-G92)/G92,0) | K92: =IF(H92<>0,H92/Resumen!$C$3,0) | L92: =IF(F92<>0,F92/Resumen!$B$11,0)
A93: LECAPSA | B93: Lecaps | C93: 2.4646869e+08 | D93: 1.85 | E93: 1.96 | F93: =C93*E93 | G93: =C93*D93 | H93: =F93-G93 | I93: =IF(G93>0,(F93-G93)/G93,0) | K93: =IF(H93<>0,H93/Resumen!$C$3,0) | L93: =IF(F93<>0,F93/Resumen!$B$11,0)
A94: LONGPesosA | B94: Long Pesos | C94: 93879019 | D94: 1.73 | E94: 2.07 | F94: =C94*E94 | G94: =C94*D94 | H94: =F94-G94 | I94: =IF(G94>0,(F94-G94)/G94,0) | K94: =IF(H94<>0,H94/Resumen!$C$3,0) | L94: =IF(F94<>0,F94/Resumen!$B$11,0)
A95: OPPORA | B95: Opportunity | C95: 1828334.6 | D95: 38.19 | E95: 38.93 | F95: =C95*E95 | G95: =C95*D95 | H95: =F95-G95 | I95: =IF(G95>0,(F95-G95)/G95,0) | K95: =IF(H95<>0,H95/Resumen!$C$3,0) | L95: =IF(F95<>0,F95/Resumen!$B$11,0)
A96: PER3A | B96: ONs FCI | C96: 2890224.8 | D96: 9 | E96: 9.19 | F96: =C96*E96 | G96: =C96*D96 | H96: =F96-G96 | I96: =IF(G96>0,(F96-G96)/G96,0) | K96: =IF(H96<>0,H96/Resumen!$C$3,0) | L96: =IF(F96<>0,F96/Resumen!$B$11,0)
A97: SOJAA | B97: Soja | C97: 46524025 | D97: 1.69 | E97: 1.61 | F97: =C97*E97 | G97: =C97*D97 | H97: =F97-G97 | I97: =IF(G97>0,(F97-G97)/G97,0) | K97: =IF(H97<>0,H97/Resumen!$C$3,0) | L97: =IF(F97<>0,F97/Resumen!$B$11,0)
A98: CPRIVADOA | B98: Crédito Privado | C98: 21848517 | D98: 1.32 | E98: 1.34 | F98: =C98*E98 | G98: =C98*D98 | H98: =F98-G98 | I98: =IF(G98>0,(F98-G98)/G98,0) | K98: =IF(H98<>0,H98/Resumen!$C$3,0) | L98: =IF(F98<>0,F98/Resumen!$B$11,0)
A99: SUBTOTAL | F99: =SUM(F88:F98) | G99: =SUM(G88:G98) | H99: =F99-G99 | I99: =IF(G99>0,(F99-G99)/G99,0) | K99: =SUM(K88:K98) | L99: =SUM(L88:L98)
A101: FCIs USD (en USD)
A102: Ticker | B102: Descripción | C102: Cantidad | D102: PPC Compra | E102: Precio Vivo | F102: Valor Actual | G102: Costo Total | H102: P&L $ | I102: P&L % | J102: Var Día % | K102: P&L USD | L102: Peso % | M102: Vencimiento | N102: Días
A103: ESTRA1A | B103: Dólar Corto Plazo | C103: 186979.26 | D103: 1.14 | E103: 1.15 | F103: =C103*E103 | G103: =C103*D103 | H103: =F103-G103 | I103: =IF(G103>0,(F103-G103)/G103,0) | K103: =IF(H103<>0,H103/Resumen!$C$3,0) | L103: =IF(F103<>0,F103/Resumen!$B$11,0)
A104: BCMMUSDA | B104: Money Market USD | C104: 120192.21 | D104: 1.02 | E104: 1.02 | F104: =C104*E104 | G104: =C104*D104 | H104: =F104-G104 | I104: =IF(G104>0,(F104-G104)/G104,0) | K104: =IF(H104<>0,H104/Resumen!$C$3,0) | L104: =IF(F104<>0,F104/Resumen!$B$11,0)
A105: BAHUSDA | B105: Corporativo USD | C105: 132699.06 | D105: 1.36 | E105: 1.4 | F105: =C105*E105 | G105: =C105*D105 | H105: =F105-G105 | I105: =IF(G105>0,(F105-G105)/G105,0) | K105: =IF(H105<>0,H105/Resumen!$C$3,0) | L105: =IF(F105<>0,F105/Resumen!$B$11,0)
A106: SUBTOTAL | F106: =SUM(F103:F105) | G106: =SUM(G103:G105) | H106: =F106-G106 | I106: =IF(G106>0,(F106-G106)/G106,0) | K106: =SUM(K103:K105) | L106: =SUM(L103:L105)
A108: LETRAS
A109: Ticker | B109: Descripción | C109: Cantidad | D109: PPC Compra | E109: Precio Vivo | F109: Valor Actual | G109: Costo Total | H109: P&L $ | I109: P&L % | J109: Var Día % | K109: P&L USD | L109: Peso % | M109: Vencimiento | N109: Días
A110: S15Y6 | B110: Lecap May 2026 | C110: 22276244 | D110: 1.03 | E110: 1.04 | F110: =C110*E110 | G110: =C110*D110 | H110: =F110-G110 | I110: =IF(G110>0,(F110-G110)/G110,0) | K110: =IF(H110<>0,H110/Resumen!$C$3,0) | L110: =IF(F110<>0,F110/Resumen!$B$11,0) | M110: 2026-05-15 | N110: 24
A111: S17L6 | B111: Lecap Jul 2026 | C111: 22696099 | D111: 1.01 | E111: 1.02 | F111: =C111*E111 | G111: =C111*D111 | H111: =F111-G111 | I111: =IF(G111>0,(F111-G111)/G111,0) | K111: =IF(H111<>0,H111/Resumen!$C$3,0) | L111: =IF(F111<>0,F111/Resumen!$B$11,0) | M111: 2026-07-17 | N111: 87
A112: S29Y6 | B112: Lecap May 2026 | C112: 51675407 | D112: 1.23 | E112: 1.29 | F112: =C112*E112 | G112: =C112*D112 | H112: =F112-G112 | I112: =IF(G112>0,(F112-G112)/G112,0) | K112: =IF(H112<>0,H112/Resumen!$C$3,0) | L112: =IF(F112<>0,F112/Resumen!$B$11,0) | M112: 2026-05-29 | N112: 38
A113: S30N6 | B113: Lecap Nov 2026 | C113: 61652044 | D113: 1.04 | E113: 1.13 | F113: =C113*E113 | G113: =C113*D113 | H113: =F113-G113 | I113: =IF(G113>0,(F113-G113)/G113,0) | K113: =IF(H113<>0,H113/Resumen!$C$3,0) | L113: =IF(F113<>0,F113/Resumen!$B$11,0) | M113: 2026-11-30 | N113: 223
A114: S30O6 | B114: Lecap Oct 2026 | C114: 19609712 | D114: 1.18 | E114: 1.2 | F114: =C114*E114 | G114: =C114*D114 | H114: =F114-G114 | I114: =IF(G114>0,(F114-G114)/G114,0) | K114: =IF(H114<>0,H114/Resumen!$C$3,0) | L114: =IF(F114<>0,F114/Resumen!$B$11,0) | M114: 2026-10-30 | N114: 192
A115: S30S6 | B115: Lecap Sep 2026 | C115: 21927733 | D115: 1.05 | E115: 1.06 | F115: =C115*E115 | G115: =C115*D115 | H115: =F115-G115 | I115: =IF(G115>0,(F115-G115)/G115,0) | K115: =IF(H115<>0,H115/Resumen!$C$3,0) | L115: =IF(F115<>0,F115/Resumen!$B$11,0) | M115: 2026-09-30 | N115: 162
A116: S31G6 | B116: Lecap Ago 2026 | C116: 58193540 | D116: 1.1 | E116: 1.17 | F116: =C116*E116 | G116: =C116*D116 | H116: =F116-G116 | I116: =IF(G116>0,(F116-G116)/G116,0) | K116: =IF(H116<>0,H116/Resumen!$C$3,0) | L116: =IF(F116<>0,F116/Resumen!$B$11,0) | M116: 2026-08-31 | N116: 132
A117: X29Y6 | B117: Lecer May 2026 | C117: 9500000 | D117: 1.11 | E117: 1.16 | F117: =C117*E117 | G117: =C117*D117 | H117: =F117-G117 | I117: =IF(G117>0,(F117-G117)/G117,0) | K117: =IF(H117<>0,H117/Resumen!$C$3,0) | L117: =IF(F117<>0,F117/Resumen!$B$11,0) | M117: 2026-05-29 | N117: 38
A118: SUBTOTAL | F118: =SUM(F110:F117) | G118: =SUM(G110:G117) | H118: =F118-G118 | I118: =IF(G118>0,(F118-G118)/G118,0) | K118: =SUM(K110:K117) | L118: =SUM(L110:L117)

Sheet Provincia
A1: BANCO PROVINCIA
A3: ACCIONES
A4: Ticker | B4: Descripción | C4: Cantidad | D4: PPC Compra | E4: Precio Vivo | F4: Valor Actual | G4: Costo Total | H4: P&L $ | I4: P&L % | J4: Var Día % | K4: P&L USD | L4: Peso % | M4: Vencimiento | N4: Días
A5: ALUA | B5: Aluar | C5: 1731 | D5: 910 | E5: =googlefinance("BCBA:ALUA","price") | F5: =C5*E5 | G5: =C5*D5 | H5: =F5-G5 | I5: =IF(G5>0,(F5-G5)/G5,0) | K5: =IF(H5<>0,H5/Resumen!$C$3,0) | L5: =IF(F5<>0,F5/Resumen!$B$11,0)
A6: BBAR | B6: BBVA Argentina | C6: 2259 | D6: 8860 | E6: =googlefinance("BCBA:BBAR","price") | F6: =C6*E6 | G6: =C6*D6 | H6: =F6-G6 | I6: =IF(G6>0,(F6-G6)/G6,0) | K6: =IF(H6<>0,H6/Resumen!$C$3,0) | L6: =IF(F6<>0,F6/Resumen!$B$11,0)
A7: BMA | B7: Banco Macro | C7: 3709 | D7: 10716 | E7: =googlefinance("BCBA:BMA","price") | F7: =C7*E7 | G7: =C7*D7 | H7: =F7-G7 | I7: =IF(G7>0,(F7-G7)/G7,0) | K7: =IF(H7<>0,H7/Resumen!$C$3,0) | L7: =IF(F7<>0,F7/Resumen!$B$11,0)
A8: CRES | B8: Cresud | C8: 10861 | D8: 928.45 | E8: =googlefinance("BCBA:CRES","price") | F8: =C8*E8 | G8: =C8*D8 | H8: =F8-G8 | I8: =IF(G8>0,(F8-G8)/G8,0) | K8: =IF(H8<>0,H8/Resumen!$C$3,0) | L8: =IF(F8<>0,F8/Resumen!$B$11,0)
A9: GGAL | B9: Grupo Fin. Galicia | C9: 34160 | D9: 5046.24 | E9: =googlefinance("BCBA:GGAL","price") | F9: =C9*E9 | G9: =C9*D9 | H9: =F9-G9 | I9: =IF(G9>0,(F9-G9)/G9,0) | K9: =IF(H9<>0,H9/Resumen!$C$3,0) | L9: =IF(F9<>0,F9/Resumen!$B$11,0)
A10: IRSA | B10: IRSA | C10: 218 | D10: 2320 | E10: =googlefinance("BCBA:IRSA","price") | F10: =C10*E10 | G10: =C10*D10 | H10: =F10-G10 | I10: =IF(G10>0,(F10-G10)/G10,0) | K10: =IF(H10<>0,H10/Resumen!$C$3,0) | L10: =IF(F10<>0,F10/Resumen!$B$11,0)
A11: METR | B11: Metrogas | C11: 24752 | D11: 2028.85 | E11: =googlefinance("BCBA:METR","price") | F11: =C11*E11 | G11: =C11*D11 | H11: =F11-G11 | I11: =IF(G11>0,(F11-G11)/G11,0) | K11: =IF(H11<>0,H11/Resumen!$C$3,0) | L11: =IF(F11<>0,F11/Resumen!$B$11,0)
A12: PAMP | B12: Pampa Energía | C12: 83344 | D12: 2584.63 | E12: =googlefinance("BCBA:PAMP","price") | F12: =C12*E12 | G12: =C12*D12 | H12: =F12-G12 | I12: =IF(G12>0,(F12-G12)/G12,0) | K12: =IF(H12<>0,H12/Resumen!$C$3,0) | L12: =IF(F12<>0,F12/Resumen!$B$11,0)
A13: TGNO4 | B13: Transp. Gas Norte | C13: 5375 | D13: 2823.53 | E13: =googlefinance("BCBA:TGNO4","price") | F13: =C13*E13 | G13: =C13*D13 | H13: =F13-G13 | I13: =IF(G13>0,(F13-G13)/G13,0) | K13: =IF(H13<>0,H13/Resumen!$C$3,0) | L13: =IF(F13<>0,F13/Resumen!$B$11,0)
A14: YPFD | B14: YPF S.A. | C14: 13637 | D14: 27476.78 | E14: =googlefinance("BCBA:YPFD","price") | F14: =C14*E14 | G14: =C14*D14 | H14: =F14-G14 | I14: =IF(G14>0,(F14-G14)/G14,0) | K14: =IF(H14<>0,H14/Resumen!$C$3,0) | L14: =IF(F14<>0,F14/Resumen!$B$11,0)
A15: SUBTOTAL | F15: =SUM(F5:F14) | G15: =SUM(G5:G14) | H15: =F15-G15 | I15: =IF(G15>0,(F15-G15)/G15,0) | K15: =SUM(K5:K14) | L15: =SUM(L5:L14)
A17: CEDEARs
A18: Ticker | B18: Descripción | C18: Cantidad | D18: PPC Compra | E18: Precio Vivo | F18: Valor Actual | G18: Costo Total | H18: P&L $ | I18: P&L % | J18: Var Día % | K18: P&L USD | L18: Peso % | M18: Vencimiento | N18: Días
A19: SPY | B19: SPDR S&P 500 | C19: 529 | D19: 28368 | E19: =googlefinance("BCBA:SPY","price") | F19: =C19*E19 | G19: =C19*D19 | H19: =F19-G19 | I19: =IF(G19>0,(F19-G19)/G19,0) | K19: =IF(H19<>0,H19/Resumen!$C$3,0) | L19: =IF(F19<>0,F19/Resumen!$B$11,0)
A20: SUBTOTAL | F20: =SUM(F19:F19) | G20: =SUM(G19:G19) | H20: =F20-G20 | I20: =IF(G20>0,(F20-G20)/G20,0) | K20: =SUM(K19:K19) | L20: =SUM(L19:L19)
A22: BONOS
A23: Ticker | B23: Descripción | C23: Cantidad | D23: PPC Compra | E23: Precio Vivo | F23: Valor Actual | G23: Costo Total | H23: P&L $ | I23: P&L % | J23: Var Día % | K23: P&L USD | L23: Peso % | M23: Vencimiento | N23: Días
A24: AL30 | B24: Bono Arg USD 2030 | C24: 331620 | D24: 669.3 | E24: 905 | F24: =C24*E24 | G24: =C24*D24 | H24: =F24-G24 | I24: =IF(G24>0,(F24-G24)/G24,0) | K24: =IF(H24<>0,H24/Resumen!$C$3,0) | L24: =IF(F24<>0,F24/Resumen!$B$11,0) | M24: 2030-07-09 | N24: 1553
A25: AL35 | B25: Bono Arg USD 2035 | C25: 117805 | D25: 576.89 | E25: 1118.96 | F25: =C25*E25 | G25: =C25*D25 | H25: =F25-G25 | I25: =IF(G25>0,(F25-G25)/G25,0) | K25: =IF(H25<>0,H25/Resumen!$C$3,0) | L25: =IF(F25<>0,F25/Resumen!$B$11,0) | M25: 2035-07-09 | N25: 3379
A26: AL41 | B26: Bono Arg USD 2041 | C26: 65502 | D26: 458 | E26: 1042 | F26: =C26*E26 | G26: =C26*D26 | H26: =F26-G26 | I26: =IF(G26>0,(F26-G26)/G26,0) | K26: =IF(H26<>0,H26/Resumen!$C$3,0) | L26: =IF(F26<>0,F26/Resumen!$B$11,0) | M26: 2041-07-09 | N26: 5571
A27: TX26 | B27: Boncer 2% 2026 | C27: 830105 | D27: 18.05 | E27: 13.53 | F27: =C27*E27 | G27: =C27*D27 | H27: =F27-G27 | I27: =IF(G27>0,(F27-G27)/G27,0) | K27: =IF(H27<>0,H27/Resumen!$C$3,0) | L27: =IF(F27<>0,F27/Resumen!$B$11,0) | M27: 2026-11-15 | N27: 221
A28: TZX26 | B28: Boncer Jun 2026 | C28: 7815600 | D28: 2.56 | E28: 3.78 | F28: =C28*E28 | G28: =C28*D28 | H28: =F28-G28 | I28: =IF(G28>0,(F28-G28)/G28,0) | K28: =IF(H28<>0,H28/Resumen!$C$3,0) | L28: =IF(F28<>0,F28/Resumen!$B$11,0) | M28: 2026-06-30 | N28: 83
A29: BPOC7 | B29: Bopreal 1C 2027 | C29: 7148 | D29: 1398.5 | E29: 1474.85 | F29: =C29*E29 | G29: =C29*D29 | H29: =F29-G29 | I29: =IF(G29>0,(F29-G29)/G29,0) | K29: =IF(H29<>0,H29/Resumen!$C$3,0) | L29: =IF(F29<>0,F29/Resumen!$B$11,0) | M29: 2027-10-31 | N29: 571
A30: BPY26 | B30: Bopreal S3 2026 | C30: 25000 | D30: 527.5 | E30: 527.5 | F30: =C30*E30 | G30: =C30*D30 | H30: =F30-G30 | I30: =IF(G30>0,(F30-G30)/G30,0) | K30: =IF(H30<>0,H30/Resumen!$C$3,0) | L30: =IF(F30<>0,F30/Resumen!$B$11,0) | M30: 2026-05-31 | N30: 53
A31: BPOA8 | B31: Bopreal 4A 2028 | C31: 8071 | D31: 1295 | E31: 1295 | F31: =C31*E31 | G31: =C31*D31 | H31: =F31-G31 | I31: =IF(G31>0,(F31-G31)/G31,0) | K31: =IF(H31<>0,H31/Resumen!$C$3,0) | L31: =IF(F31<>0,F31/Resumen!$B$11,0) | M31: 2028-10-31 | N31: 924
A32: GD38 | B32: Global USD 2038 | C32: 34969 | D32: 1193 | E32: 1193 | F32: =C32*E32 | G32: =C32*D32 | H32: =F32-G32 | I32: =IF(G32>0,(F32-G32)/G32,0) | K32: =IF(H32<>0,H32/Resumen!$C$3,0) | L32: =IF(F32<>0,F32/Resumen!$B$11,0) | M32: 2038-01-09 | N32: 4294
A33: SUBTOTAL | F33: =SUM(F24:F32) | G33: =SUM(G24:G32) | H33: =F33-G33 | I33: =IF(G33>0,(F33-G33)/G33,0) | K33: =SUM(K24:K32) | L33: =SUM(L24:L32)
A35: FCIs
A36: Ticker | B36: Descripción | C36: Cantidad | D36: PPC Compra | E36: Precio Vivo | F36: Valor Actual | G36: Costo Total | H36: P&L $ | I36: P&L % | J36: Var Día % | K36: P&L USD | L36: Peso % | M36: Vencimiento | N36: Días
A37: RAICES 7x24 | B37: Raíces Ahorro Pesos | C37: 13715547 | D37: 34.89 | E37: 35.19 | F37: =C37*E37 | G37: =C37*D37 | H37: =F37-G37 | I37: =IF(G37>0,(F37-G37)/G37,0) | K37: =IF(H37<>0,H37/Resumen!$C$3,0) | L37: =IF(F37<>0,F37/Resumen!$B$11,0)
A38: RAICES USD | B38: Raíces Dólares Plus (USD) | C38: 65642.587 | D38: 1.268 | E38: 1.295 | F38: =C38*E38 | G38: =C38*D38 | H38: =F38-G38 | I38: =IF(G38>0,(F38-G38)/G38,0) | K38: =IF(H38<>0,H38/Resumen!$C$3,0) | L38: =IF(F38<>0,F38/Resumen!$B$11,0)
A39: SUBTOTAL | F39: =SUM(F37:F38) | G39: =SUM(G37:G38) | H39: =F39-G39 | I39: =IF(G39>0,(F39-G39)/G39,0) | K39: =SUM(K37:K38) | L39: =SUM(L37:L38)

Sheet Instrucciones
A1: CÓMO FUNCIONA
A3: Columna D (azul) = PPC Compra → editable, tu costo de compra
A4: Columna E (verde) = Precio Vivo → GOOGLEFINANCE automático para acciones/CEDEARs
A5: Columna E (gris) = Precio manual → bonos, ONs, FCIs, letras (editá cuando actualices)
A6: Columnas F-I = se calculan solas (valor, costo, P&L $, P&L %)
A8: GOOGLEFINANCE solo funciona en Google Sheets, NO en Excel de escritorio.
